<level>
  <settings gravityX="0" gravityY="9.8" width="1000" height="1000" id="fa_3" planetId="fa"/>
  <planes>
    <plane distance="70" name="space">
      <obj type="GraphicObj" assetClass="fa_gr_bg_space1" id="29" x="1248" y="120" settings="{dynamic:b1,z:7}" assetPackage="fa"/>
      <obj type="GraphicObj" assetClass="fa_gr_bg_space_moon1" id="246" x="1146.5" y="-89.5" settings="{z:7,dynamic:b1}" assetPackage="fa"/>
      <obj type="GraphicObj" assetClass="fa_gr_bg_space2" id="652" x="48" y="120" settings="{z:7}" assetPackage="fa"/>
      <obj type="GraphicObj" assetClass="fa_gr_bg_space2" id="653" x="648" y="120" settings="{z:7}" assetPackage="fa"/>
      <obj type="GraphicObj" assetClass="fa_gr_bg_space2" id="654" x="648" y="-480" settings="{z:7}" assetPackage="fa"/>
      <obj type="GraphicObj" assetClass="fa_gr_bg_space2" id="655" x="48" y="-480" settings="{z:7}" assetPackage="fa"/>
      <obj type="GraphicObj" assetClass="fa_gr_bg_space2" id="656" x="1248" y="-480" settings="{z:7}" assetPackage="fa"/>
      <obj type="GraphicObj" assetClass="fa_gr_bg_space2" id="690" x="1848" y="120" settings="{z:7}" assetPackage="fa"/>
      <obj type="GraphicObj" assetClass="fa_gr_bg_space2" id="691" x="1848" y="-480" settings="{z:7}" assetPackage="fa"/>
    </plane>
    <plane distance="50" name="planet1">
      <obj type="GraphicObj" assetClass="fa_gr_bg_space_cel2" id="243" x="1043.5" y="-264.5" settings="{z:7,dynamic:b1}" assetPackage="fa"/>
    </plane>
    <plane distance="40" name="planet2">
      <obj type="GraphicObj" assetClass="fa_gr_bg_space_cel1" id="242" x="205.5" y="-382.5" settings="{z:7,dynamic:b1}" assetPackage="fa"/>
      <obj type="GraphicObj" assetClass="fa_gr_bg_silhouette_2_2" id="346" x="732" y="255" settings="{z:0,dynamic:b1}" assetPackage="fa"/>
      <obj type="GraphicObj" assetClass="fa_gr_bg_silhouette_3_2" id="347" x="297" y="259" settings="{z:0,dynamic:b1}" assetPackage="fa"/>
      <obj type="GraphicObj" assetClass="fa_gr_bg_silhouette_1_2" id="348" x="1160" y="298" settings="{z:7,dynamic:b1}" assetPackage="fa"/>
      <obj type="GraphicObj" assetClass="fa_gr_bg_silhouette_overlap_2" id="356" x="970" y="344" settings="{z:7,dynamic:b1}" assetPackage="fa"/>
      <obj type="GraphicObj" assetClass="fa_gr_bg_silhouette_overlap_2" id="357" x="480" y="345" settings="{z:7,dynamic:b1}" assetPackage="fa"/>
      <obj type="GraphicObj" assetClass="fa_gr_bg_silhouette_1_2" id="767" x="1592" y="297.9" settings="{z:7,dynamic:b1}" assetPackage="fa"/>
    </plane>
    <plane distance="20" name="house">
      <obj type="GraphicObj" assetClass="fa_gr_bg_silhouette_2_1" id="338" x="412" y="57" settings="{dynamic:b1,z:0}" assetPackage="fa"/>
      <obj type="GraphicObj" assetClass="fa_gr_bg_silhouette_1_1" id="340" x="1014" y="119" settings="{dynamic:b1,z:0}" assetPackage="fa"/>
      <obj type="GraphicObj" assetClass="fa_gr_bg_silhouette_3_1" id="341" x="1541" y="61" settings="{dynamic:b1,z:0}" assetPackage="fa"/>
      <obj type="GraphicObj" assetClass="fa_gr_bg_silhouette_1_1" id="343" x="2056" y="119" settings="{dynamic:b1,z:0}" assetPackage="fa"/>
      <obj type="GraphicObj" assetClass="fa_gr_bg_silhouette_overlap_1" id="353" x="695" y="133" settings="{z:7,dynamic:b1}" assetPackage="fa"/>
      <obj type="GraphicObj" assetClass="fa_gr_bg_silhouette_overlap_1" id="354" x="1293" y="133" settings="{z:7,dynamic:b1}" assetPackage="fa"/>
      <obj type="GraphicObj" assetClass="fa_gr_bg_silhouette_overlap_1" id="355" x="1773" y="133" settings="{z:7,dynamic:b1}" assetPackage="fa"/>
    </plane>
    <plane distance="10" name="gamePlane" physics="1">
      <obj type="GraphicObj" assetClass="fa_gr_bg_item4" id="5" x="-372" y="-103" settings="{z:1,dynamic:b1}" assetPackage="fa"/>
      <obj type="BasicPhysicsObj" assetClass="fa_pl_05_12x6_floor" id="39" x="-156" y="-348" settings="{dynamic:b1,z:2}" assetPackage="fa"/>
      <obj type="BasicPhysicsObj" assetClass="fa_pl_05_12x6_floor" id="40" x="-300" y="-348" settings="{dynamic:b1,z:2}" assetPackage="fa"/>
      <obj type="BasicPhysicsObj" assetClass="fa_gr_pipe_2x12_v" id="45" x="-155" y="-183" settings="{dynamic:b1,z:2}" assetPackage="fa"/>
      <obj type="BasicPhysicsObj" assetClass="fa_pl_05_12x6_floor" id="58" x="-443.95" y="-348" settings="{dynamic:b1,z:2}" assetPackage="fa"/>
      <obj type="BasicPhysicsObj" assetClass="fa_pl_05_12x6_floor" id="61" x="491.95" y="-348" settings="{dynamic:b1,z:2}" assetPackage="fa"/>
      <obj type="BasicPhysicsObj" assetClass="fa_pl_05_12x6_floor" id="62" x="636" y="-348" settings="{dynamic:b1,z:2}" assetPackage="fa"/>
      <obj type="BasicPhysicsObj" assetClass="fa_pl_05_12x6_floor" id="63" x="780" y="-348" settings="{dynamic:b1,z:2}" assetPackage="fa"/>
      <obj type="BasicPhysicsObj" assetClass="fa_gr_plate_9x5_02" id="67" x="-66" y="234" settings="{z:2,dynamic:b1}" assetPackage="fa"/>
      <obj type="BasicPhysicsObj" assetClass="fa_gr_plate_9x5_02" id="68" x="42" y="234" settings="{z:2,dynamic:b1}" assetPackage="fa"/>
      <obj type="BasicPhysicsObj" assetClass="fa_gr_plate_9x5_02" id="69" x="150" y="234" settings="{z:2,dynamic:b1}" assetPackage="fa"/>
      <obj type="BasicPhysicsObj" assetClass="fa_gr_plate_9x5_02" id="70" x="258" y="234" settings="{z:2,dynamic:b1}" assetPackage="fa"/>
      <obj type="BasicPhysicsObj" assetClass="fa_gr_pipe_conn2_v" id="72" x="-154" y="-84" settings="{z:2,dynamic:b1}" assetPackage="fa"/>
      <obj type="BasicPhysicsObj" assetClass="fa_gr_pipe_2x6_v" id="74" x="-155" y="-12" settings="{z:2,dynamic:b1}" assetPackage="fa"/>
      <obj type="BasicPhysicsObj" assetClass="fa_gr_pipe_2x6_h" id="87" x="-216" y="-83" settings="{z:2,dynamic:b1}" assetPackage="fa"/>
      <obj type="BasicPhysicsObj" assetClass="fa_gr_pipe_bend_4" id="88" x="-274.5" y="-71" settings="{z:2,dynamic:b1}" assetPackage="fa"/>
      <obj type="BasicPhysicsObj" assetClass="fa_gr_pipe_2x12_v" id="89" x="-287" y="20.95" settings="{z:2,dynamic:b1}" assetPackage="fa"/>
      <obj type="BasicPhysicsObj" assetClass="fa_gr_pipe_2x12_v" id="90" x="-287" y="153" settings="{z:2,dynamic:b1}" assetPackage="fa"/>
      <obj type="BasicPhysicsObj" assetClass="fa_gr_pipe_bend_2" id="91" x="-106.5" y="-95" settings="{z:2,dynamic:b1}" assetPackage="fa"/>
      <obj type="BasicPhysicsObj" assetClass="fa_gr_pipe_valveEnd" id="92" x="-96" y="-124.95" settings="{z:2,dynamic:b1}" assetPackage="fa"/>
      <obj type="BasicPhysicsObj" assetClass="fa_gr_plate_9x5_02" id="97" x="42" y="294" settings="{z:2,dynamic:b1}" assetPackage="fa"/>
      <obj type="BasicPhysicsObj" assetClass="fa_gr_plate_9x5_02" id="98" x="-66" y="294" settings="{z:2,dynamic:b1}" assetPackage="fa"/>
      <obj type="BasicPhysicsObj" assetClass="fa_gr_plate_9x5_02" id="107" x="-174" y="234" settings="{z:2,dynamic:b1}" assetPackage="fa"/>
      <obj type="BasicPhysicsObj" assetClass="fa_gr_plate_9x5_05" id="112" x="258" y="294" settings="{z:2,dynamic:b1}" assetPackage="fa"/>
      <obj type="BasicPhysicsObj" assetClass="fa_gr_plate_9x5_01" id="125" x="222" y="-402" settings="{z:2,dynamic:b1}" assetPackage="fa"/>
      <obj type="BasicPhysicsObj" assetClass="fa_gr_plate_9x5_01" id="126" x="222" y="-462" settings="{z:2,dynamic:b1}" assetPackage="fa"/>
      <obj type="BasicPhysicsObj" assetClass="fa_gr_plate_9x5_01" id="127" x="222" y="-522" settings="{z:2,dynamic:b1}" assetPackage="fa"/>
      <obj type="BasicPhysicsObj" assetClass="fa_pl_05_12x6_floor" id="135" x="-588" y="-348" settings="{dynamic:b1,z:2}" assetPackage="fa"/>
      <obj type="BasicPhysicsObj" assetClass="fa_pl_05_12x6_floor" id="136" x="348" y="-348" settings="{dynamic:b1,z:2}" assetPackage="fa"/>
      <obj type="BasicPhysicsObj" assetClass="fa_gr_plate_9x5_01" id="138" x="222" y="-642" settings="{z:2,dynamic:b1}" assetPackage="fa"/>
      <obj type="GraphicObj" assetClass="fa_pl_antenna_base" id="139" x="603" y="-397.5" settings="{z:3,dynamic:b1}" assetPackage="fa"/>
      <obj type="BasicPhysicsObj" assetClass="fa_pl_antenna_poleEnd_12x1" id="140" x="677" y="-480.5" settings="{z:1,dynamic:b1}" assetPackage="fa"/>
      <obj type="GraphicObj" assetClass="fa_pl_antenna_connect_03" id="145" x="607.5" y="-480" settings="{z:3,dynamic:b1}" assetPackage="fa"/>
      <obj type="GraphicObj" assetClass="fa_pl_antenna_connect_04" id="146" x="602" y="-655" settings="{z:3,dynamic:b1}" assetPackage="fa"/>
      <obj type="BasicPhysicsObj" assetClass="fa_pl_antenna_poleEnd_12x1" id="156" x="814" y="-655.45" settings="{z:2,dynamic:b1}" assetPackage="fa"/>
      <obj type="BasicPhysicsObj" assetClass="fa_gr_plate_9x5_06" id="162" x="222" y="-582" settings="{z:2,dynamic:b1}" assetPackage="fa"/>
      <obj type="BasicPhysicsObj" assetClass="fa_gr_plate_9x5_07" id="163" x="-30" y="-582" settings="{z:2,dynamic:b1}" assetPackage="fa"/>
      <obj type="BasicPhysicsObj" assetClass="fa_gr_plate_9x5_05" id="164" x="-30" y="-642" settings="{z:2,dynamic:b1}" assetPackage="fa"/>
      <obj type="BasicPhysicsObj" assetClass="fa_gr_plate_9x5_02" id="166" x="222" y="-342" settings="{z:2,dynamic:b1}" assetPackage="fa"/>
      <obj type="BasicPhysicsObj" assetClass="fa_gr_plate_9x5_02" id="167" x="-30" y="-342" settings="{z:2,dynamic:b1}" assetPackage="fa"/>
      <obj type="BasicPhysicsObj" assetClass="fa_gr_pipe_2x12_v" id="169" x="37" y="-543" settings="{z:2,dynamic:b1}" assetPackage="fa"/>
      <obj type="BasicPhysicsObj" assetClass="fa_gr_pipe_2x12_v" id="170" x="37" y="-411" settings="{z:2,dynamic:b1}" assetPackage="fa"/>
      <obj type="BasicPhysicsObj" assetClass="fa_gr_pipe_bend_2" id="172" x="26" y="-247.95" settings="{z:2,dynamic:b1}" assetPackage="fa"/>
      <obj type="BasicPhysicsObj" assetClass="fa_gr_pipe_2x12_v" id="174" x="37" y="-679.95" settings="{z:2,dynamic:b1}" assetPackage="fa"/>
      <obj type="BasicPhysicsObj" assetClass="fa_gr_pipe_valveEnd" id="176" x="37" y="-890" settings="{z:2,dynamic:b1}" assetPackage="fa"/>
      <obj type="BasicPhysicsObj" assetClass="fa_gr_pipe_2x6_v" id="177" x="37" y="-306" settings="{z:2,dynamic:b1}" assetPackage="fa"/>
      <obj type="BasicPhysicsObj" assetClass="fa_gr_pipe_2x12_h" id="178" x="-67" y="-236" settings="{z:4,dynamic:b1}" assetPackage="fa"/>
      <obj type="BasicPhysicsObj" assetClass="fa_gr_pipe_2x12_h" id="179" x="-204" y="-236" settings="{z:4,dynamic:b1}" assetPackage="fa"/>
      <obj type="BasicPhysicsObj" assetClass="fa_gr_pipe_2x12_h" id="180" x="-341.95" y="-236" settings="{z:2,dynamic:b1}" assetPackage="fa"/>
      <obj type="BasicPhysicsObj" assetClass="fa_gr_pipe_2x12_h" id="181" x="-480" y="-236" settings="{z:2,dynamic:b1}" assetPackage="fa"/>
      <obj type="BasicPhysicsObj" assetClass="fa_gr_pipe_2x12_v" id="182" x="-147.95" y="-452" settings="{dynamic:b1,z:2}" assetPackage="fa"/>
      <obj type="BasicPhysicsObj" assetClass="fa_gr_pipe_bend_3" id="184" x="-160" y="-545.45" settings="{z:2,dynamic:b1}" assetPackage="fa"/>
      <obj type="BasicPhysicsObj" assetClass="fa_pl_05_12x6_floor" id="187" x="924" y="-348" settings="{dynamic:b1,z:2}" assetPackage="fa"/>
      <obj type="BasicPhysicsObj" assetClass="fa_pl_05_12x6_floor" id="188" x="1068" y="-348" settings="{dynamic:b1,z:2}" assetPackage="fa"/>
      <obj type="BasicPhysicsObj" assetClass="fa_pl_05_12x6_floor" id="189" x="1212" y="-348" settings="{dynamic:b1,z:2}" assetPackage="fa"/>
      <obj type="BasicPhysicsObj" assetClass="fa_pl_05_12x6_floor" id="190" x="1356" y="-348" settings="{dynamic:b1,z:2}" assetPackage="fa"/>
      <obj type="BasicPhysicsObj" assetClass="fa_pl_05_12x6_floor" id="191" x="1500" y="-348" settings="{dynamic:b1,z:2}" assetPackage="fa"/>
      <obj type="BasicPhysicsObj" assetClass="fa_pl_05_12x6_floor" id="192" x="1644" y="-348" settings="{dynamic:b1,z:2}" assetPackage="fa"/>
      <obj type="BasicPhysicsObj" assetClass="fa_pl_05_12x6_floor" id="193" x="1788" y="-348" settings="{dynamic:b1,z:2}" assetPackage="fa"/>
      <obj type="BasicPhysicsObj" assetClass="fa_pl_05_12x6_floor" id="194" x="2220" y="-348" settings="{dynamic:b1,z:2}" assetPackage="fa"/>
      <obj type="BasicPhysicsObj" assetClass="fa_pl_05_12x6_floor" id="195" x="2076" y="-348" settings="{dynamic:b1,z:2}" assetPackage="fa"/>
      <obj type="BasicPhysicsObj" assetClass="fa_pl_05_12x6_floor" id="196" x="1932" y="-348" settings="{dynamic:b1,z:2}" assetPackage="fa"/>
      <obj type="BasicPhysicsObj" assetClass="fa_pl_05_12x6_floor" id="197" x="2364" y="-348" settings="{dynamic:b1,z:2}" assetPackage="fa"/>
      <obj type="GraphicObj" assetClass="fa_pl_antenna_pole_12x1_v" id="215" x="602.5" y="-483" settings="{z:2,dynamic:b1}" assetPackage="fa"/>
      <obj type="GraphicObj" assetClass="fa_pl_antenna_pole_12x1_v" id="216" x="602.5" y="-626" settings="{z:2,dynamic:b1}" assetPackage="fa"/>
      <obj type="GraphicObj" assetClass="fa_pl_antenna_pole_12x1_v" id="217" x="602.5" y="-768" settings="{z:2,dynamic:b1}" assetPackage="fa"/>
      <obj type="GraphicObj" assetClass="fa_pl_antenna_pole_12x1_v" id="218" x="602.5" y="-902" settings="{z:2,dynamic:b1}" assetPackage="fa"/>
      <obj type="MoveablePlatform" assetClass="fa_pl_03_grey_6x2" id="221" x="108" y="168" settings="{soundSettings:{minVolumeDistance:30,dynamicVolume:b1,maxVolumeDistance:4,loopCount:0,maxVolume:14,isMusic:b0,dynamicPanning:b1},distance:28,dynamic:b1,speed:4,angle:270,z:7}" assetPackage="fa"/>
      <obj type="BasicPhysicsObj" assetClass="fa_gr_pipe_bend_4" id="226" x="240" y="182" settings="{z:1,dynamic:b1}" assetPackage="fa"/>
      <obj type="BasicPhysicsObj" assetClass="fa_pl_antenna_pole_12x1_h" id="228" x="672.95" y="-655.45" settings="{dynamic:b1,z:2}" assetPackage="fa"/>
      <obj type="GraphicObj" assetClass="fa_pl_antenna_base" id="230" x="1179" y="-400.5" settings="{z:3,dynamic:b1}" assetPackage="fa"/>
      <obj type="GraphicObj" assetClass="fa_pl_antenna_pole_12x1_v" id="231" x="1179.5" y="-480" settings="{z:0,dynamic:b1}" assetPackage="fa"/>
      <obj type="BasicPhysicsObj" assetClass="fa_pl_antenna_pole_12x1_h" id="233" x="1116" y="-548.5" settings="{dynamic:b1,z:2}" assetPackage="fa"/>
      <obj type="BasicPhysicsObj" assetClass="fa_pl_antenna_pole_12x1_h" id="234" x="976" y="-548.5" settings="{dynamic:b1,z:2}" assetPackage="fa"/>
      <obj type="GraphicObj" assetClass="fa_pl_antenna_pole_12x1_v" id="235" x="1179.5" y="-624" settings="{z:0,dynamic:b1}" assetPackage="fa"/>
      <obj type="GraphicObj" assetClass="fa_pl_antenna_pole_12x1_v" id="236" x="1179.5" y="-766" settings="{z:0,dynamic:b1}" assetPackage="fa"/>
      <obj type="GraphicObj" assetClass="fa_pl_antenna_connect_04" id="237" x="1179" y="-549" settings="{dynamic:b1,z:3}" assetPackage="fa"/>
      <obj type="BasicPhysicsObj" assetClass="fa_pl_antenna_pole_12x1_h" id="239" x="529.95" y="-758.5" settings="{dynamic:b1,z:2}" assetPackage="fa"/>
      <obj type="GraphicObj" assetClass="fa_pl_antenna_connect_03" id="240" x="1183.5" y="-647" settings="{dynamic:b1,z:3}" assetPackage="fa"/>
      <obj type="GraphicObj" assetClass="fa_gr_bg_item0b" id="247" x="622" y="134" settings="{z:0,dynamic:b1}" assetPackage="fa"/>
      <obj type="GraphicObj" assetClass="fa_gr_bg_item0b" id="248" x="-386" y="134" settings="{z:0,dynamic:b1}" assetPackage="fa"/>
      <obj type="BasicPhysicsObj" assetClass="fa_gr_pipe_2x12_v" id="249" x="325" y="65.95" settings="{dynamic:b1,z:2}" assetPackage="fa"/>
      <obj type="BasicPhysicsObj" assetClass="fa_gr_pipe_2x12_v" id="250" x="-155" y="92.95" settings="{dynamic:b1,z:2}" assetPackage="fa"/>
      <obj type="BasicPhysicsObj" assetClass="fa_gr_pipe_2x12_v" id="251" x="-287" y="285" settings="{z:2,dynamic:b1}" assetPackage="fa"/>
      <obj type="BasicPhysicsObj" assetClass="fa_gr_pipe_2x6_v" id="255" x="-155" y="192" settings="{z:1,dynamic:b1}" assetPackage="fa"/>
      <obj type="BasicPhysicsObj" assetClass="fa_gr_pipe_2x12_v" id="256" x="-287" y="417" settings="{z:2,dynamic:b1}" assetPackage="fa"/>
      <obj type="BasicPhysicsObj" assetClass="fa_gr_pipe_2x12_v" id="260" x="325" y="275" settings="{dynamic:b1,z:2}" assetPackage="fa"/>
      <obj type="BasicPhysicsObj" assetClass="fa_gr_pipe_2x12_v" id="262" x="325" y="393" settings="{dynamic:b1,z:2}" assetPackage="fa"/>
      <obj type="BasicPhysicsObj" assetClass="fa_gr_pipe_2x6_h" id="267" x="386.95" y="171" settings="{dynamic:b1,z:1}" assetPackage="fa"/>
      <obj type="BasicPhysicsObj" assetClass="fa_gr_pipe_2x6_h" id="268" x="458" y="171" settings="{dynamic:b1,z:1}" assetPackage="fa"/>
      <obj type="BasicPhysicsObj" assetClass="fa_gr_pipe_bend_2" id="270" x="518.5" y="159" settings="{dynamic:b1,z:2}" assetPackage="fa"/>
      <obj type="BasicPhysicsObj" assetClass="fa_gr_pipe_valveEnd" id="271" x="530" y="129" settings="{dynamic:b1,z:2}" assetPackage="fa"/>
      <obj type="BasicPhysicsObj" assetClass="fa_gr_pipe_conn2_v" id="272" x="325" y="171" settings="{dynamic:b1,z:2}" assetPackage="fa"/>
      <obj type="BasicPhysicsObj" assetClass="fa_gr_pipe_2x3_h" id="273" x="280.95" y="171" settings="{dynamic:b1,z:2}" assetPackage="fa"/>
      <obj type="BasicPhysicsObj" assetClass="fa_gr_pipe_valve" id="274" x="325" y="-26.45" settings="{dynamic:b1,z:2}" assetPackage="fa"/>
      <obj type="BasicPhysicsObj" assetClass="fa_gr_pipe_2x12_v" id="275" x="325" y="-119" settings="{dynamic:b1,z:2}" assetPackage="fa"/>
      <obj type="BasicPhysicsObj" assetClass="fa_gr_pipe_2x12_v" id="277" x="325" y="-243" settings="{dynamic:b1,z:1}" assetPackage="fa"/>
      <obj type="BasicPhysicsObj" assetClass="fa_pl_05_12x6_floor" id="302" x="2508" y="-348" settings="{dynamic:b1,z:2}" assetPackage="fa"/>
      <obj type="BasicPhysicsObj" assetClass="fa_pl_05_12x6_floor" id="303" x="2652" y="-348" settings="{dynamic:b1,z:2}" assetPackage="fa"/>
      <obj type="BasicPhysicsObj" assetClass="fa_pl_05_12x6_floor" id="304" x="2796" y="-348" settings="{dynamic:b1,z:2}" assetPackage="fa"/>
      <obj type="BasicPhysicsObj" assetClass="fa_pl_05_12x6_floor" id="305" x="2940" y="-348" settings="{dynamic:b1,z:2}" assetPackage="fa"/>
      <obj type="BasicPhysicsObj" assetClass="fa_pl_05_12x6_floor" id="312" x="3084" y="-348" settings="{dynamic:b1,z:2}" assetPackage="fa"/>
      <obj type="BasicPhysicsObj" assetClass="fa_pl_05_12x6_floor" id="313" x="3228" y="-348" settings="{dynamic:b1,z:2}" assetPackage="fa"/>
      <obj type="GraphicObj" assetClass="fa_gr_bg_pipe" id="345" x="110" y="-456" settings="{z:0,dynamic:b1}" assetPackage="fa"/>
      <obj type="BasicPhysicsObj" assetClass="fa_gr_pipe_2x12_v" id="358" x="37" y="-816.95" settings="{z:2,dynamic:b1}" assetPackage="fa"/>
      <obj type="GraphicObj" assetClass="fa_pl_antenna_pole_12x1_v" id="362" x="1179.5" y="-900" settings="{z:0,dynamic:b1}" assetPackage="fa"/>
      <obj type="GraphicObj" assetClass="fa_pl_antenna_pole_12x1_v" id="363" x="1179.5" y="-1032" settings="{z:0,dynamic:b1}" assetPackage="fa"/>
      <obj type="GraphicObj" assetClass="fa_pl_antenna_pole_12x1_v" id="364" x="1179.5" y="-1164" settings="{z:0,dynamic:b1}" assetPackage="fa"/>
      <obj type="GraphicObj" assetClass="fa_pl_antenna_base" id="365" x="1887" y="-400.5" settings="{z:3,dynamic:b1}" assetPackage="fa"/>
      <obj type="GraphicObj" assetClass="fa_pl_antenna_pole_12x1_v" id="366" x="1887.5" y="-482" settings="{z:0,dynamic:b1}" assetPackage="fa"/>
      <obj type="GraphicObj" assetClass="fa_pl_antenna_pole_12x1_v" id="367" x="1887.5" y="-625" settings="{z:0,dynamic:b1}" assetPackage="fa"/>
      <obj type="GraphicObj" assetClass="fa_pl_antenna_pole_12x1_v" id="368" x="1887.5" y="-768" settings="{z:0,dynamic:b1}" assetPackage="fa"/>
      <obj type="GraphicObj" assetClass="fa_pl_antenna_pole_12x1_v" id="369" x="1887.5" y="-910" settings="{z:0,dynamic:b1}" assetPackage="fa"/>
      <obj type="GraphicObj" assetClass="fa_pl_antenna_pole_12x1_v" id="370" x="1887.5" y="-1044" settings="{z:0,dynamic:b1}" assetPackage="fa"/>
      <obj type="BasicPhysicsObj" assetClass="fa_pl_antenna_pole_12x1_h" id="371" x="1812" y="-740.5" settings="{z:2,dynamic:b1}" assetPackage="fa"/>
      <obj type="GraphicObj" assetClass="fa_pl_antenna_connect_04" id="372" x="1887" y="-740" settings="{z:3,dynamic:b1}" assetPackage="fa"/>
      <obj type="BasicPhysicsObj" assetClass="fa_pl_antenna_pole_12x1_h" id="373" x="1956" y="-740.5" settings="{z:2,dynamic:b1}" assetPackage="fa"/>
      <obj type="BasicPhysicsObj" assetClass="fa_pl_antenna_pole_12x1_h" id="374" x="1668" y="-740.5" settings="{z:2,dynamic:b1}" assetPackage="fa"/>
      <obj type="GraphicObj" assetClass="fa_pl_antenna_connect_04" id="375" x="1743" y="-742" settings="{z:3,dynamic:b1}" assetPackage="fa"/>
      <obj type="GraphicObj" assetClass="fa_pl_antenna_pole_12x1_v" id="376" x="1743.5" y="-672" settings="{z:0,dynamic:b1}" assetPackage="fa"/>
      <obj type="GraphicObj" assetClass="fa_pl_antenna_pole_12x1_v" id="377" x="1743.5" y="-816" settings="{z:0,dynamic:b1}" assetPackage="fa"/>
      <obj type="GraphicObj" assetClass="fa_pl_antenna_connect_03" id="378" x="1183.5" y="-1160" settings="{z:3,dynamic:b1}" assetPackage="fa"/>
      <obj type="BasicPhysicsObj" assetClass="fa_pl_antenna_pole_12x1_h" id="379" x="1260" y="-1160.5" settings="{z:2,dynamic:b1}" assetPackage="fa"/>
      <obj type="BasicPhysicsObj" assetClass="fa_pl_antenna_pole_12x1_h" id="380" x="1402" y="-1160.5" settings="{z:2,dynamic:b1}" assetPackage="fa"/>
      <obj type="BasicPhysicsObj" assetClass="fa_pl_antenna_poleEnd_12x1" id="381" x="1543" y="-1160.5" settings="{z:2,dynamic:b1}" assetPackage="fa"/>
      <obj type="Portal" assetClass="un_ob_portalIn" id="383" x="1414" y="-925.5" settings="{dynamic:b1,z:2,pairedPortalLoc:{y:-1489.5,x:1510}}" assetPackage="un"/>
      <obj type="GraphicObj" assetClass="fa_pl_antenna_pole_12x1_v" id="384" x="1179.5" y="-1305" settings="{z:0,dynamic:b1}" assetPackage="fa"/>
      <obj type="GraphicObj" assetClass="fa_pl_antenna_pole_12x1_v" id="385" x="1179.5" y="-1447" settings="{z:0,dynamic:b1}" assetPackage="fa"/>
      <obj type="GraphicObj" assetClass="fa_pl_antenna_pole_12x1_v" id="386" x="1179.5" y="-1590" settings="{z:0,dynamic:b1}" assetPackage="fa"/>
      <obj type="GraphicObj" assetClass="fa_pl_antenna_base" id="387" x="2787" y="-400.5" settings="{z:3,dynamic:b1}" assetPackage="fa"/>
      <obj type="GraphicObj" assetClass="fa_pl_antenna_pole_12x1_v" id="388" x="2787.5" y="-480" settings="{z:0,dynamic:b1}" assetPackage="fa"/>
      <obj type="GraphicObj" assetClass="fa_pl_antenna_pole_12x1_v" id="389" x="2787.5" y="-624" settings="{z:0,dynamic:b1}" assetPackage="fa"/>
      <obj type="BasicPhysicsObj" assetClass="fa_pl_antenna_pole_12x1_h" id="390" x="2713" y="-482.45" settings="{z:2,dynamic:b1}" assetPackage="fa"/>
      <obj type="BasicPhysicsObj" assetClass="fa_pl_antenna_pole_12x1_h" id="391" x="2861" y="-584.5" settings="{z:2,dynamic:b1}" assetPackage="fa"/>
      <obj type="BasicPhysicsObj" assetClass="fa_pl_antenna_pole_12x1_h" id="392" x="2712" y="-695.5" settings="{z:2,dynamic:b1}" assetPackage="fa"/>
      <obj type="GraphicObj" assetClass="fa_pl_antenna_pole_12x1_v" id="393" x="2787.5" y="-767" settings="{z:0,dynamic:b1}" assetPackage="fa"/>
      <obj type="GraphicObj" assetClass="fa_pl_antenna_pole_12x1_v" id="394" x="2787.5" y="-910" settings="{z:0,dynamic:b1}" assetPackage="fa"/>
      <obj type="Portal" assetClass="un_ob_portalIn" id="396" x="3098.5" y="-801.5" settings="{pairedPortalLoc:{x:2693.5,y:-1407.5},dynamic:b1,z:2}" assetPackage="un"/>
      <obj type="PickupObj" assetClass="un_ob_win_01_small" id="398" x="1235.5" y="-1188.5" settings="{z:6,dynamic:b1}" assetPackage="un"/>
      <obj type="PickupObj" assetClass="un_ob_win_01_small" id="399" x="1283.5" y="-1188.5" settings="{z:6,dynamic:b1}" assetPackage="un"/>
      <obj type="PickupObj" assetClass="un_ob_win_01_small" id="400" x="1331.5" y="-1188.5" settings="{z:6,dynamic:b1}" assetPackage="un"/>
      <obj type="PickupObj" assetClass="un_ob_win_01_small" id="401" x="1379.5" y="-1188.5" settings="{z:6,dynamic:b1}" assetPackage="un"/>
      <obj type="PickupObj" assetClass="un_ob_win_01_small" id="402" x="1427.5" y="-1188.5" settings="{z:6,dynamic:b1}" assetPackage="un"/>
      <obj type="PickupObj" assetClass="un_ob_win_01_small" id="403" x="1475.5" y="-1188.5" settings="{z:6,dynamic:b1}" assetPackage="un"/>
      <obj type="PickupObj" assetClass="un_ob_win_01_small" id="404" x="1523.5" y="-1188.5" settings="{z:6,dynamic:b1}" assetPackage="un"/>
      <obj type="BasicPhysicsObj" assetClass="fa_pl_antenna_pole_12x1_h" id="405" x="1527" y="-740.5" settings="{z:2,dynamic:b1}" assetPackage="fa"/>
      <obj type="GraphicObj" assetClass="fa_pl_antenna_pole_12x1_v" id="406" x="2787.5" y="-1053" settings="{z:0,dynamic:b1}" assetPackage="fa"/>
      <obj type="BasicPhysicsObj" assetClass="fa_pl_antenna_pole_12x1_h" id="407" x="2709" y="-1111.5" settings="{z:2,dynamic:b1}" assetPackage="fa"/>
      <obj type="BasicPhysicsObj" assetClass="fa_pl_antenna_pole_12x1_h" id="408" x="2566" y="-1111.5" settings="{z:2,dynamic:b1}" assetPackage="fa"/>
      <obj type="BasicPhysicsObj" assetClass="fa_pl_antenna_pole_12x1_h" id="409" x="2424" y="-1111.5" settings="{z:2,dynamic:b1}" assetPackage="fa"/>
      <obj type="GraphicObj" assetClass="fa_pl_antenna_pole_12x1_v" id="411" x="2637.5" y="-1185" settings="{z:0,dynamic:b1}" assetPackage="fa"/>
      <obj type="GraphicObj" assetClass="fa_pl_antenna_pole_12x1_v" id="412" x="2637.5" y="-1328" settings="{z:0,dynamic:b1}" assetPackage="fa"/>
      <obj type="BasicPhysicsObj" assetClass="fa_pl_antenna_pole_12x1_h" id="413" x="2710" y="-1256.5" settings="{z:2,dynamic:b1}" assetPackage="fa"/>
      <obj type="PickupObj" assetClass="un_ob_win_01_small" id="417" x="1472.8" y="-795.2" settings="{z:6,dynamic:b1}" assetPackage="un"/>
      <obj type="PickupObj" assetClass="un_ob_win_01_small" id="418" x="1520.8" y="-795.2" settings="{z:6,dynamic:b1}" assetPackage="un"/>
      <obj type="PickupObj" assetClass="un_ob_win_01_small" id="419" x="1568.8" y="-795.2" settings="{z:6,dynamic:b1}" assetPackage="un"/>
      <obj type="PickupObj" assetClass="un_ob_win_01_small" id="420" x="1616.8" y="-795.2" settings="{z:6,dynamic:b1}" assetPackage="un"/>
      <obj type="GraphicObj" assetClass="fa_pl_antenna_connect_04" id="424" x="2786" y="-1112" settings="{dynamic:b1,z:3}" assetPackage="fa"/>
      <obj type="SoundClip" assetClass="un_ob_soundIcon" id="429" x="2192" y="-2805.95" settings="{z:2,soundSettings:{maxVolume:78,minVolumeDistance:109,fileName:'fa_snd_music_3',loopCount:0,dynamicVolume:b1,isMusic:b0,dynamicPanning:b0,maxVolumeDistance:90}}" assetPackage="un"/>
      <obj type="PickupObj" assetClass="un_ob_win_01_small" id="430" x="116.8" y="-39.2" settings="{z:6}" assetPackage="un"/>
      <obj type="PickupObj" assetClass="un_ob_win_01_small" id="431" x="116.8" y="-87.2" settings="{z:6}" assetPackage="un"/>
      <obj type="PickupObj" assetClass="un_ob_win_01_small" id="432" x="116.8" y="-135.2" settings="{z:6}" assetPackage="un"/>
      <obj type="PickupObj" assetClass="un_ob_win_01_small" id="433" x="116.8" y="-183.2" settings="{z:6}" assetPackage="un"/>
      <obj type="PickupObj" assetClass="un_ob_win_01_small" id="434" x="116.8" y="-231.2" settings="{z:6}" assetPackage="un"/>
      <obj type="PickupObj" assetClass="un_ob_win_01_small" id="435" x="116.8" y="-279.2" settings="{z:6}" assetPackage="un"/>
      <obj type="PickupObj" assetClass="un_ob_win_01_small" id="436" x="116.8" y="-327.2" settings="{z:6}" assetPackage="un"/>
      <obj type="PickupObj" assetClass="un_ob_win_01_small" id="437" x="116.8" y="-375.2" settings="{z:6}" assetPackage="un"/>
      <obj type="PickupObj" assetClass="un_ob_win_01_small" id="438" x="116.8" y="-423.2" settings="{z:6}" assetPackage="un"/>
      <obj type="PickupObj" assetClass="un_ob_win_01_small" id="439" x="116.8" y="-471.2" settings="{z:6}" assetPackage="un"/>
      <obj type="PickupObj" assetClass="un_ob_win_01_small" id="440" x="116.8" y="-519.2" settings="{z:6}" assetPackage="un"/>
      <obj type="PickupObj" assetClass="un_ob_win_01_small" id="441" x="116.8" y="-567.2" settings="{z:6}" assetPackage="un"/>
      <obj type="GravitySetter" assetClass="un_ob_gravitySetter" id="442" x="105.5" y="-602.5" settings="{z:1,gravityX:0,gravityY:6}" assetPackage="un"/>
      <obj type="GravitySetter" assetClass="un_ob_gravitySetter" id="443" x="105.5" y="-410.5" settings="{z:1,gravityX:0,gravityY:9.5}" assetPackage="un"/>
      <obj type="Checkpoint" assetClass="un_ob_startPoint" id="444" x="-96.2" y="-0.15" settings="{z:2}" assetPackage="un"/>
      <obj type="Checkpoint" assetClass="un_ob_exitDoor" id="445" x="3373.65" y="-437.3" settings="{z:3}" assetPackage="un"/>
      <obj type="FilmClipObj" assetClass="un_ob_filmClipViewer" id="446" x="2388" y="-378" settings="{z:3,url1:'fa_3a',url2:'fa_3a'}" assetPackage="un"/>
      <obj type="GraphicObj" assetClass="fa_gr_plate_9x5_09" id="447" x="3246" y="-282" settings="{z:2}" assetPackage="fa"/>
      <obj type="GraphicObj" assetClass="fa_gr_plate_9x5_09" id="448" x="3138" y="-282" settings="{z:2}" assetPackage="fa"/>
      <obj type="GraphicObj" assetClass="fa_gr_plate_9x5_09" id="449" x="3030" y="-282" settings="{z:2}" assetPackage="fa"/>
      <obj type="GraphicObj" assetClass="fa_gr_plate_9x5_09" id="450" x="2922" y="-282" settings="{z:2}" assetPackage="fa"/>
      <obj type="GraphicObj" assetClass="fa_gr_plate_9x5_09" id="451" x="2814" y="-282" settings="{z:2}" assetPackage="fa"/>
      <obj type="GraphicObj" assetClass="fa_gr_plate_9x5_09" id="452" x="2706" y="-282" settings="{z:2}" assetPackage="fa"/>
      <obj type="GraphicObj" assetClass="fa_gr_plate_9x5_09" id="453" x="2598" y="-282" settings="{z:2}" assetPackage="fa"/>
      <obj type="GraphicObj" assetClass="fa_gr_plate_9x5_09" id="454" x="2490" y="-282" settings="{z:2}" assetPackage="fa"/>
      <obj type="GraphicObj" assetClass="fa_gr_plate_9x5_09" id="455" x="2382" y="-282" settings="{z:2}" assetPackage="fa"/>
      <obj type="GraphicObj" assetClass="fa_gr_plate_9x5_09" id="458" x="2274" y="-282" settings="{z:2}" assetPackage="fa"/>
      <obj type="GraphicObj" assetClass="fa_gr_plate_9x5_09" id="459" x="2166" y="-282" settings="{z:2}" assetPackage="fa"/>
      <obj type="GraphicObj" assetClass="fa_gr_plate_9x5_09" id="460" x="2058" y="-282" settings="{z:2}" assetPackage="fa"/>
      <obj type="GraphicObj" assetClass="fa_gr_plate_9x5_09" id="461" x="1950" y="-282" settings="{z:2}" assetPackage="fa"/>
      <obj type="GraphicObj" assetClass="fa_gr_plate_9x5_09" id="462" x="1842" y="-282" settings="{z:2}" assetPackage="fa"/>
      <obj type="GraphicObj" assetClass="fa_gr_plate_9x5_09" id="463" x="1734" y="-282" settings="{z:2}" assetPackage="fa"/>
      <obj type="GraphicObj" assetClass="fa_gr_plate_9x5_09" id="464" x="1626" y="-282" settings="{z:2}" assetPackage="fa"/>
      <obj type="GraphicObj" assetClass="fa_gr_plate_9x5_09" id="465" x="1518" y="-282" settings="{z:2}" assetPackage="fa"/>
      <obj type="GraphicObj" assetClass="fa_gr_plate_9x5_09" id="466" x="1410" y="-282" settings="{z:2}" assetPackage="fa"/>
      <obj type="GraphicObj" assetClass="fa_gr_plate_9x5_09" id="467" x="1302" y="-282" settings="{z:2}" assetPackage="fa"/>
      <obj type="GraphicObj" assetClass="fa_gr_plate_9x5_09" id="468" x="1194" y="-282" settings="{z:2}" assetPackage="fa"/>
      <obj type="BasicPhysicsObj" assetClass="fa_pl_antenna_poleEnd_12x1" id="477" x="1258.95" y="-647.5" settings="{z:2}" assetPackage="fa"/>
      <obj type="GraphicObj" assetClass="fa_pl_antenna_connect_03" id="478" x="2791" y="-583" settings="{z:3}" assetPackage="fa"/>
      <obj type="GraphicObj" assetClass="fa_pl_antenna_connect_03" id="479" x="2641" y="-1255" settings="{z:3}" assetPackage="fa"/>
      <obj type="BasicPhysicsObj" assetClass="fa_pl_antenna_poleEnd_12x1" id="480" x="2852" y="-1256.5" settings="{z:2}" assetPackage="fa"/>
      <obj type="PickupObj" assetClass="un_ob_win_micro" id="481" x="2801.5" y="-606.5" settings="{z:6}" assetPackage="un"/>
      <obj type="PickupObj" assetClass="un_ob_win_micro" id="482" x="2825.5" y="-606.5" settings="{z:6}" assetPackage="un"/>
      <obj type="PickupObj" assetClass="un_ob_win_micro" id="483" x="2849.5" y="-606.5" settings="{z:6}" assetPackage="un"/>
      <obj type="PickupObj" assetClass="un_ob_win_micro" id="484" x="2873.5" y="-606.5" settings="{z:6}" assetPackage="un"/>
      <obj type="PickupObj" assetClass="un_ob_win_micro" id="485" x="2897.5" y="-606.5" settings="{z:6}" assetPackage="un"/>
      <obj type="PickupObj" assetClass="un_ob_win_micro" id="486" x="2921.5" y="-606.5" settings="{z:6}" assetPackage="un"/>
      <obj type="PickupObj" assetClass="un_ob_win_micro" id="487" x="1469.5" y="-762.5" settings="{z:6}" assetPackage="un"/>
      <obj type="PickupObj" assetClass="un_ob_win_micro" id="488" x="1493.5" y="-762.5" settings="{z:6}" assetPackage="un"/>
      <obj type="PickupObj" assetClass="un_ob_win_micro" id="489" x="1517.5" y="-762.5" settings="{z:6}" assetPackage="un"/>
      <obj type="PickupObj" assetClass="un_ob_win_micro" id="490" x="1541.5" y="-762.5" settings="{z:6}" assetPackage="un"/>
      <obj type="PickupObj" assetClass="un_ob_win_micro" id="491" x="1565.5" y="-762.5" settings="{z:6}" assetPackage="un"/>
      <obj type="PickupObj" assetClass="un_ob_win_micro" id="492" x="1589.5" y="-762.5" settings="{z:6}" assetPackage="un"/>
      <obj type="PickupObj" assetClass="un_ob_win_micro" id="493" x="1613.5" y="-762.5" settings="{z:6}" assetPackage="un"/>
      <obj type="PickupObj" assetClass="un_ob_win_micro" id="494" x="1637.5" y="-762.5" settings="{z:6}" assetPackage="un"/>
      <obj type="PickupObj" assetClass="un_ob_win_micro" id="495" x="1661.5" y="-762.5" settings="{z:6}" assetPackage="un"/>
      <obj type="PickupObj" assetClass="un_ob_win_micro" id="496" x="1685.5" y="-762.5" settings="{z:6}" assetPackage="un"/>
      <obj type="PickupObj" assetClass="un_ob_win_micro" id="497" x="1709.5" y="-762.5" settings="{z:6}" assetPackage="un"/>
      <obj type="PickupObj" assetClass="un_ob_win_micro" id="499" x="1193.5" y="-1182.5" settings="{z:6}" assetPackage="un"/>
      <obj type="PickupObj" assetClass="un_ob_win_micro" id="500" x="1193.5" y="-1206.5" settings="{z:6}" assetPackage="un"/>
      <obj type="PickupObj" assetClass="un_ob_win_micro" id="501" x="1193.5" y="-1230.5" settings="{z:6}" assetPackage="un"/>
      <obj type="PickupObj" assetClass="un_ob_win_micro" id="502" x="1193.5" y="-1254.5" settings="{z:6}" assetPackage="un"/>
      <obj type="PickupObj" assetClass="un_ob_win_micro" id="503" x="1193.5" y="-1278.5" settings="{z:6}" assetPackage="un"/>
      <obj type="PickupObj" assetClass="un_ob_win_micro" id="504" x="1193.5" y="-1302.5" settings="{z:6}" assetPackage="un"/>
      <obj type="PickupObj" assetClass="un_ob_win_micro" id="505" x="1193.5" y="-1326.5" settings="{z:6}" assetPackage="un"/>
      <obj type="PickupObj" assetClass="un_ob_win_micro" id="506" x="1193.5" y="-1350.5" settings="{z:6}" assetPackage="un"/>
      <obj type="PickupObj" assetClass="un_ob_win_micro" id="507" x="1193.5" y="-1374.5" settings="{z:6}" assetPackage="un"/>
      <obj type="PickupObj" assetClass="un_ob_win_micro" id="508" x="1769.5" y="-762.5" settings="{z:6}" assetPackage="un"/>
      <obj type="PickupObj" assetClass="un_ob_win_micro" id="509" x="1769.5" y="-786.5" settings="{z:6}" assetPackage="un"/>
      <obj type="PickupObj" assetClass="un_ob_win_micro" id="510" x="1769.5" y="-810.5" settings="{z:6}" assetPackage="un"/>
      <obj type="PickupObj" assetClass="un_ob_win_micro" id="511" x="1769.5" y="-834.5" settings="{z:6}" assetPackage="un"/>
      <obj type="PickupObj" assetClass="un_ob_win_micro" id="512" x="1769.5" y="-858.5" settings="{z:6}" assetPackage="un"/>
      <obj type="PickupObj" assetClass="un_ob_win_micro" id="513" x="1769.5" y="-882.5" settings="{z:6}" assetPackage="un"/>
      <obj type="GraphicObj" assetClass="fa_pl_antenna_connect_04" id="514" x="2787" y="-481" settings="{z:3}" assetPackage="fa"/>
      <obj type="GraphicObj" assetClass="fa_pl_antenna_connect_04" id="515" x="2788" y="-694" settings="{z:3}" assetPackage="fa"/>
      <obj type="GraphicObj" assetClass="fa_pl_antenna_connect_04" id="516" x="2638" y="-1110" settings="{dynamic:b1,z:3}" assetPackage="fa"/>
      <obj type="PickupObj" assetClass="un_ob_win_01_small" id="517" x="2663.5" y="-1284.5" settings="{z:6}" assetPackage="un"/>
      <obj type="PickupObj" assetClass="un_ob_win_01_small" id="518" x="2699.5" y="-1284.5" settings="{z:6}" assetPackage="un"/>
      <obj type="PickupObj" assetClass="un_ob_win_01_small" id="519" x="2735.45" y="-1284.5" settings="{z:6}" assetPackage="un"/>
      <obj type="PickupObj" assetClass="un_ob_win_01_small" id="520" x="2771.5" y="-1284.5" settings="{z:6}" assetPackage="un"/>
      <obj type="PickupObj" assetClass="un_ob_win_01_small" id="521" x="2807.5" y="-1284.5" settings="{z:6}" assetPackage="un"/>
      <obj type="PickupObj" assetClass="un_ob_win_01_small" id="522" x="2843.5" y="-1284.5" settings="{z:6}" assetPackage="un"/>
      <obj type="PickupObj" assetClass="un_ob_win_01_small" id="523" x="2879.5" y="-1284.5" settings="{z:6}" assetPackage="un"/>
      <obj type="BasicPhysicsObj" assetClass="fa_pl_antenna_poleEnd_12x1" id="524" x="3156" y="-1112.5" settings="{z:2}" assetPackage="fa"/>
      <obj type="BasicPhysicsObj" assetClass="fa_pl_05_12x6_floor" id="525" x="3372" y="-348" settings="{dynamic:b1,z:2}" assetPackage="fa"/>
      <obj type="GraphicObj" assetClass="fa_gr_plate_9x5_09" id="527" x="3354" y="-282" settings="{z:2}" assetPackage="fa"/>
      <obj type="GraphicObj" assetClass="fa_gr_plate_9x5_09" id="528" x="3462" y="-282" settings="{z:2}" assetPackage="fa"/>
      <obj type="GraphicObj" assetClass="fa_gr_plate_9x5_09" id="529" x="3570" y="-282" settings="{z:2}" assetPackage="fa"/>
      <obj type="BasicPhysicsObj" assetClass="fa_pl_05_6x6_floor" id="532" x="3480" y="-348" settings="{z:2}" assetPackage="fa"/>
      <obj type="GraphicObj" assetClass="fa_gr_plate_9x5_09" id="533" x="3570" y="-342" settings="{z:2}" assetPackage="fa"/>
      <obj type="GraphicObj" assetClass="fa_gr_plate_9x5_09" id="546" x="3678" y="-822" settings="{z:2}" assetPackage="fa"/>
      <obj type="GraphicObj" assetClass="fa_gr_plate_9x5_09" id="557" x="3678" y="-522" settings="{z:2}" assetPackage="fa"/>
      <obj type="GraphicObj" assetClass="fa_gr_plate_9x5_09" id="558" x="3678" y="-462" settings="{z:2}" assetPackage="fa"/>
      <obj type="GraphicObj" assetClass="fa_gr_plate_9x5_09" id="560" x="3678" y="-342" settings="{z:2}" assetPackage="fa"/>
      <obj type="GraphicObj" assetClass="fa_gr_plate_9x5_09" id="561" x="3678" y="-282" settings="{z:2}" assetPackage="fa"/>
      <obj type="BasicPhysicsObj" assetClass="fa_gr_plate_9x5_01" id="562" x="3570" y="-402" settings="{z:2}" assetPackage="fa"/>
      <obj type="BasicPhysicsObj" assetClass="fa_gr_plate_9x5_01" id="563" x="3570" y="-462" settings="{z:2}" assetPackage="fa"/>
      <obj type="BasicPhysicsObj" assetClass="fa_gr_plate_9x5_01" id="564" x="3570" y="-522" settings="{z:2}" assetPackage="fa"/>
      <obj type="BasicPhysicsObj" assetClass="fa_gr_plate_9x5_01" id="565" x="3570" y="-582" settings="{z:2}" assetPackage="fa"/>
      <obj type="BasicPhysicsObj" assetClass="fa_gr_plate_9x5_01" id="566" x="3570" y="-642" settings="{z:2}" assetPackage="fa"/>
      <obj type="GraphicObj" assetClass="fa_gr_plate_9x5_09" id="567" x="3786" y="-282" settings="{z:2}" assetPackage="fa"/>
      <obj type="GraphicObj" assetClass="fa_gr_plate_9x5_09" id="568" x="3786" y="-342" settings="{z:2}" assetPackage="fa"/>
      <obj type="GraphicObj" assetClass="fa_gr_plate_9x5_09" id="569" x="3786" y="-402" settings="{z:2}" assetPackage="fa"/>
      <obj type="GraphicObj" assetClass="fa_pl_antenna_connect_02" id="584" x="2787" y="-842" settings="{z:3}" assetPackage="fa"/>
      <obj type="GraphicObj" assetClass="fa_pl_antenna_connect_02" id="585" x="2788" y="-980" settings="{z:4}" assetPackage="fa"/>
      <obj type="GraphicObj" assetClass="fa_pl_antenna_connect_02" id="586" x="2787" y="-551" settings="{z:3}" assetPackage="fa"/>
      <obj type="GraphicObj" assetClass="fa_pl_antenna_connect_02" id="587" x="1888" y="-555" settings="{z:3}" assetPackage="fa"/>
      <obj type="GraphicObj" assetClass="fa_pl_antenna_connect_02" id="588" x="1888" y="-691" settings="{z:3}" assetPackage="fa"/>
      <obj type="GraphicObj" assetClass="fa_pl_antenna_connect_02" id="589" x="1888" y="-840" settings="{z:3}" assetPackage="fa"/>
      <obj type="GraphicObj" assetClass="fa_pl_antenna_connect_02" id="590" x="1888" y="-979" settings="{z:3}" assetPackage="fa"/>
      <obj type="GraphicObj" assetClass="fa_pl_antenna_connect_02" id="591" x="1180" y="-1102" settings="{z:3}" assetPackage="fa"/>
      <obj type="GraphicObj" assetClass="fa_pl_antenna_connect_02" id="592" x="1181" y="-968" settings="{z:3}" assetPackage="fa"/>
      <obj type="GraphicObj" assetClass="fa_pl_antenna_connect_02" id="593" x="1180" y="-822" settings="{z:3}" assetPackage="fa"/>
      <obj type="GraphicObj" assetClass="fa_pl_antenna_connect_02" id="594" x="1180" y="-692" settings="{z:3}" assetPackage="fa"/>
      <obj type="GraphicObj" assetClass="fa_pl_antenna_connect_02" id="595" x="603" y="-556" settings="{z:3}" assetPackage="fa"/>
      <obj type="GraphicObj" assetClass="fa_pl_antenna_connect_02" id="596" x="602" y="-693" settings="{z:3}" assetPackage="fa"/>
      <obj type="GraphicObj" assetClass="fa_pl_antenna_connect_04" id="597" x="602" y="-757" settings="{z:3,dynamic:b1}" assetPackage="fa"/>
      <obj type="SoundClip" assetClass="un_ob_soundIcon" id="598" x="43.2" y="271.2" settings="{soundSettings:{minVolumeDistance:37,maxVolume:65,fileName:'fa_snd_indoor_bg_b',loopCount:0,dynamicVolume:b1,isMusic:b0,dynamicPanning:b1,maxVolumeDistance:26},z:4}" assetPackage="un"/>
      <obj type="GraphicObj" assetClass="fa_pl_antenna_connect_02" id="599" x="603" y="-837" settings="{z:3}" assetPackage="fa"/>
      <obj type="PickupObj" assetClass="un_ob_wreck_09" id="601" x="3795.5" y="-632.5" settings="{z:6}" assetPackage="un"/>
      <obj type="Checkpoint" assetClass="un_ob_checkpoint" id="602" x="241" y="-713.45" settings="{z:2}" assetPackage="un"/>
      <obj type="PickupObj" assetClass="un_ob_win_04_big" id="603" x="1266.5" y="-689.5" settings="{z:6}" assetPackage="un"/>
      <obj type="PickupObj" assetClass="un_ob_win_04_big" id="604" x="2706.5" y="-533.5" settings="{z:6}" assetPackage="un"/>
      <obj type="PickupObj" assetClass="un_ob_win_micro" id="605" x="293.5" y="137.5" settings="{z:6}" assetPackage="un"/>
      <obj type="PickupObj" assetClass="un_ob_win_micro" id="606" x="293.5" y="113.5" settings="{z:6}" assetPackage="un"/>
      <obj type="PickupObj" assetClass="un_ob_win_micro" id="607" x="293.5" y="89.5" settings="{z:6}" assetPackage="un"/>
      <obj type="PickupObj" assetClass="un_ob_win_micro" id="608" x="293.5" y="65.5" settings="{z:6}" assetPackage="un"/>
      <obj type="PickupObj" assetClass="un_ob_win_micro" id="609" x="293.5" y="41.5" settings="{z:6}" assetPackage="un"/>
      <obj type="PickupObj" assetClass="un_ob_win_micro" id="610" x="293.5" y="17.5" settings="{z:6}" assetPackage="un"/>
      <obj type="PickupObj" assetClass="un_ob_win_micro" id="611" x="269.5" y="137.5" settings="{z:6}" assetPackage="un"/>
      <obj type="PickupObj" assetClass="un_ob_win_micro" id="612" x="269.5" y="113.5" settings="{z:6}" assetPackage="un"/>
      <obj type="PickupObj" assetClass="un_ob_win_micro" id="613" x="269.5" y="89.5" settings="{z:6}" assetPackage="un"/>
      <obj type="PickupObj" assetClass="un_ob_win_micro" id="614" x="269.5" y="65.5" settings="{z:6}" assetPackage="un"/>
      <obj type="PickupObj" assetClass="un_ob_win_micro" id="615" x="269.5" y="17.5" settings="{z:6}" assetPackage="un"/>
      <obj type="PickupObj" assetClass="un_ob_win_micro" id="616" x="269.5" y="41.5" settings="{z:6}" assetPackage="un"/>
      <obj type="GraphicObj" assetClass="fa_gr_bg_item4" id="617" x="636" y="-103" settings="{z:1,dynamic:b1}" assetPackage="fa"/>
      <obj type="PickupObj" assetClass="un_ob_win_micro" id="618" x="269.5" y="41.5" settings="{z:6}" assetPackage="un"/>
      <obj type="PickupObj" assetClass="un_ob_win_micro" id="620" x="245.5" y="137.5" settings="{z:6}" assetPackage="un"/>
      <obj type="PickupObj" assetClass="un_ob_win_micro" id="621" x="245.5" y="113.5" settings="{z:6}" assetPackage="un"/>
      <obj type="PickupObj" assetClass="un_ob_win_micro" id="622" x="245.5" y="89.5" settings="{z:6}" assetPackage="un"/>
      <obj type="PickupObj" assetClass="un_ob_win_micro" id="623" x="245.5" y="65.5" settings="{z:6}" assetPackage="un"/>
      <obj type="PickupObj" assetClass="un_ob_win_micro" id="624" x="245.5" y="41.5" settings="{z:6}" assetPackage="un"/>
      <obj type="PickupObj" assetClass="un_ob_win_micro" id="625" x="245.5" y="17.5" settings="{z:6}" assetPackage="un"/>
      <obj type="GraphicObj" assetClass="fa_gr_plate_9x5_09" id="626" x="-174" y="294" settings="{z:2}" assetPackage="fa"/>
      <obj type="GraphicObj" assetClass="fa_gr_plate_9x5_09" id="627" x="150" y="294" settings="{z:2}" assetPackage="fa"/>
      <obj type="GraphicObj" assetClass="fa_gr_plate_9x5_09" id="628" x="258" y="354" settings="{z:2}" assetPackage="fa"/>
      <obj type="GraphicObj" assetClass="fa_gr_plate_9x5_09" id="629" x="150" y="354" settings="{z:2}" assetPackage="fa"/>
      <obj type="GraphicObj" assetClass="fa_gr_plate_9x5_09" id="630" x="42" y="354" settings="{z:2}" assetPackage="fa"/>
      <obj type="GraphicObj" assetClass="fa_gr_plate_9x5_09" id="631" x="-66" y="354" settings="{z:2}" assetPackage="fa"/>
      <obj type="GraphicObj" assetClass="fa_gr_plate_9x5_09" id="632" x="-174" y="354" settings="{z:2}" assetPackage="fa"/>
      <obj type="GraphicObj" assetClass="fa_gr_plate_9x5_09" id="633" x="-138" y="-282" settings="{z:2}" assetPackage="fa"/>
      <obj type="GraphicObj" assetClass="fa_gr_plate_9x5_09" id="634" x="-30" y="-282" settings="{z:2}" assetPackage="fa"/>
      <obj type="GraphicObj" assetClass="fa_gr_plate_9x5_09" id="635" x="-246" y="-282" settings="{z:2}" assetPackage="fa"/>
      <obj type="GraphicObj" assetClass="fa_gr_plate_9x5_09" id="636" x="-354" y="-282" settings="{z:2}" assetPackage="fa"/>
      <obj type="GraphicObj" assetClass="fa_gr_plate_9x5_09" id="637" x="-462" y="-282" settings="{z:2}" assetPackage="fa"/>
      <obj type="GraphicObj" assetClass="fa_gr_plate_9x5_09" id="638" x="-570" y="-282" settings="{z:2}" assetPackage="fa"/>
      <obj type="GraphicObj" assetClass="fa_gr_plate_9x5_09" id="639" x="-30" y="-402" settings="{z:2}" assetPackage="fa"/>
      <obj type="GraphicObj" assetClass="fa_gr_plate_9x5_09" id="640" x="-30" y="-462" settings="{z:2}" assetPackage="fa"/>
      <obj type="GraphicObj" assetClass="fa_gr_plate_9x5_09" id="641" x="-30" y="-522" settings="{z:2}" assetPackage="fa"/>
      <obj type="GraphicObj" assetClass="fa_gr_plate_9x5_09" id="643" x="330" y="-282" settings="{z:2}" assetPackage="fa"/>
      <obj type="GraphicObj" assetClass="fa_gr_plate_9x5_09" id="644" x="438" y="-282" settings="{z:2}" assetPackage="fa"/>
      <obj type="BasicPhysicsObj" assetClass="fa_gr_plate_9x5_01" id="645" x="222" y="-282" settings="{z:2,dynamic:b1}" assetPackage="fa"/>
      <obj type="GraphicObj" assetClass="fa_gr_plate_9x5_09" id="646" x="546" y="-282" settings="{z:2}" assetPackage="fa"/>
      <obj type="GraphicObj" assetClass="fa_gr_plate_9x5_09" id="647" x="654" y="-282" settings="{z:2}" assetPackage="fa"/>
      <obj type="GraphicObj" assetClass="fa_gr_plate_9x5_09" id="648" x="762" y="-282" settings="{z:2}" assetPackage="fa"/>
      <obj type="GraphicObj" assetClass="fa_gr_plate_9x5_09" id="649" x="870" y="-282" settings="{z:2}" assetPackage="fa"/>
      <obj type="GraphicObj" assetClass="fa_gr_plate_9x5_09" id="650" x="978" y="-282" settings="{z:2}" assetPackage="fa"/>
      <obj type="GraphicObj" assetClass="fa_gr_plate_9x5_09" id="651" x="1086" y="-282" settings="{z:2}" assetPackage="fa"/>
      <obj type="BasicPhysicsObj" assetClass="fa_pl_antenna_pole_12x1_h" id="657" x="2868" y="-1112.5" settings="{z:2,dynamic:b1}" assetPackage="fa"/>
      <obj type="BasicPhysicsObj" assetClass="fa_pl_antenna_pole_12x1_h" id="658" x="3012" y="-1112.5" settings="{z:2,dynamic:b1}" assetPackage="fa"/>
      <obj type="BasicPhysicsObj" assetClass="fa_gr_plate_9x5_01" id="661" x="3570" y="-702" settings="{z:2}" assetPackage="fa"/>
      <obj type="BasicPhysicsObj" assetClass="fa_gr_plate_9x5_01" id="662" x="3570" y="-762" settings="{z:2}" assetPackage="fa"/>
      <obj type="BasicPhysicsObj" assetClass="fa_gr_plate_9x5_01" id="663" x="3570" y="-822" settings="{z:2}" assetPackage="fa"/>
      <obj type="BasicPhysicsObj" assetClass="fa_gr_plate_9x5_01" id="664" x="3570" y="-882" settings="{z:2}" assetPackage="fa"/>
      <obj type="BasicPhysicsObj" assetClass="fa_gr_plate_9x5_01" id="665" x="3570" y="-942" settings="{z:2}" assetPackage="fa"/>
      <obj type="BasicPhysicsObj" assetClass="fa_gr_plate_9x5_01" id="666" x="3678" y="-942" settings="{z:2}" assetPackage="fa"/>
      <obj type="BasicPhysicsObj" assetClass="fa_gr_plate_9x5_01" id="667" x="3786" y="-942" settings="{z:2}" assetPackage="fa"/>
      <obj type="BasicPhysicsObj" assetClass="fa_gr_plate_9x5_01" id="668" x="3894" y="-942" settings="{z:2}" assetPackage="fa"/>
      <obj type="BasicPhysicsObj" assetClass="fa_gr_plate_9x5_01" id="669" x="4002" y="-942" settings="{z:2}" assetPackage="fa"/>
      <obj type="GraphicObj" assetClass="fa_gr_plate_9x5_09" id="670" x="3678" y="-882" settings="{z:2}" assetPackage="fa"/>
      <obj type="GraphicObj" assetClass="fa_gr_plate_9x5_09" id="671" x="3786" y="-882" settings="{z:2}" assetPackage="fa"/>
      <obj type="GraphicObj" assetClass="fa_gr_plate_9x5_09" id="672" x="3894" y="-882" settings="{z:2}" assetPackage="fa"/>
      <obj type="GraphicObj" assetClass="fa_gr_plate_9x5_09" id="673" x="4002" y="-882" settings="{z:2}" assetPackage="fa"/>
      <obj type="GraphicObj" assetClass="fa_gr_plate_9x5_09" id="675" x="4218" y="-882" settings="{z:2}" assetPackage="fa"/>
      <obj type="GraphicObj" assetClass="fa_gr_plate_9x5_09" id="676" x="4326" y="-882" settings="{z:2}" assetPackage="fa"/>
      <obj type="GraphicObj" assetClass="fa_gr_plate_9x5_09" id="677" x="4434" y="-882" settings="{z:2}" assetPackage="fa"/>
      <obj type="BasicPhysicsObj" assetClass="fa_gr_plate_9x5_01" id="678" x="4110" y="-942" settings="{z:2}" assetPackage="fa"/>
      <obj type="BasicPhysicsObj" assetClass="fa_gr_plate_9x5_01" id="679" x="4218" y="-942" settings="{z:2}" assetPackage="fa"/>
      <obj type="BasicPhysicsObj" assetClass="fa_gr_plate_9x5_01" id="680" x="4434" y="-941.95" settings="{z:2}" assetPackage="fa"/>
      <obj type="BasicPhysicsObj" assetClass="fa_gr_plate_9x5_01" id="681" x="4326" y="-942" settings="{z:2}" assetPackage="fa"/>
      <obj type="GraphicObj" assetClass="fa_gr_plate_9x5_09" id="701" x="3894" y="-402" settings="{z:2}" assetPackage="fa"/>
      <obj type="GraphicObj" assetClass="fa_gr_plate_9x5_09" id="702" x="3894" y="-342" settings="{z:2}" assetPackage="fa"/>
      <obj type="GraphicObj" assetClass="fa_gr_plate_9x5_09" id="703" x="4002" y="-402" settings="{z:2}" assetPackage="fa"/>
      <obj type="GraphicObj" assetClass="fa_gr_plate_9x5_09" id="704" x="4002" y="-342" settings="{z:2}" assetPackage="fa"/>
      <obj type="GraphicObj" assetClass="fa_gr_plate_9x5_09" id="705" x="4002" y="-282" settings="{z:2}" assetPackage="fa"/>
      <obj type="GraphicObj" assetClass="fa_gr_plate_9x5_09" id="706" x="3894" y="-282" settings="{z:2}" assetPackage="fa"/>
      <obj type="GraphicObj" assetClass="fa_gr_plate_9x5_09" id="714" x="4110" y="-882" settings="{z:2}" assetPackage="fa"/>
      <obj type="GraphicObj" assetClass="fa_gr_plate_9x5_09" id="721" x="4218" y="-822" settings="{z:2}" assetPackage="fa"/>
      <obj type="GraphicObj" assetClass="fa_gr_plate_9x5_09" id="722" x="4326" y="-822" settings="{z:2}" assetPackage="fa"/>
      <obj type="GraphicObj" assetClass="fa_gr_plate_9x5_09" id="723" x="4434" y="-822" settings="{z:2}" assetPackage="fa"/>
      <obj type="GraphicObj" assetClass="fa_gr_plate_9x5_09" id="725" x="4650" y="-822" settings="{z:2}" assetPackage="fa"/>
      <obj type="GraphicObj" assetClass="fa_gr_plate_9x5_09" id="726" x="4758" y="-822" settings="{z:2}" assetPackage="fa"/>
      <obj type="GraphicObj" assetClass="fa_gr_plate_9x5_09" id="728" x="4326" y="-762" settings="{z:2}" assetPackage="fa"/>
      <obj type="GraphicObj" assetClass="fa_gr_plate_9x5_09" id="729" x="4434" y="-762" settings="{z:2}" assetPackage="fa"/>
      <obj type="GraphicObj" assetClass="fa_gr_plate_9x5_09" id="731" x="4650" y="-762" settings="{z:2}" assetPackage="fa"/>
      <obj type="GraphicObj" assetClass="fa_gr_plate_9x5_09" id="732" x="4758" y="-762" settings="{z:2}" assetPackage="fa"/>
      <obj type="GraphicObj" assetClass="fa_gr_plate_9x5_09" id="734" x="4110" y="-402" settings="{z:2}" assetPackage="fa"/>
      <obj type="GraphicObj" assetClass="fa_gr_plate_9x5_09" id="735" x="4110" y="-342" settings="{z:2}" assetPackage="fa"/>
      <obj type="GraphicObj" assetClass="fa_gr_plate_9x5_09" id="736" x="4110" y="-282" settings="{z:2}" assetPackage="fa"/>
      <obj type="GraphicObj" assetClass="fa_gr_plate_9x5_09" id="738" x="4542" y="-822" settings="{z:2}" assetPackage="fa"/>
      <obj type="GraphicObj" assetClass="fa_gr_plate_9x5_09" id="739" x="4542" y="-762" settings="{z:2}" assetPackage="fa"/>
      <obj type="GraphicObj" assetClass="fa_gr_plate_9x5_09" id="740" x="4542" y="-702" settings="{z:2}" assetPackage="fa"/>
      <obj type="GraphicObj" assetClass="fa_gr_plate_9x5_09" id="741" x="4542" y="-642" settings="{z:2}" assetPackage="fa"/>
      <obj type="GraphicObj" assetClass="fa_gr_plate_9x5_09" id="742" x="4758" y="-702" settings="{z:2}" assetPackage="fa"/>
      <obj type="GraphicObj" assetClass="fa_gr_plate_9x5_09" id="743" x="4650" y="-702" settings="{z:2}" assetPackage="fa"/>
      <obj type="GraphicObj" assetClass="fa_gr_plate_9x5_09" id="745" x="4434" y="-702" settings="{z:2}" assetPackage="fa"/>
      <obj type="GraphicObj" assetClass="fa_gr_plate_9x5_09" id="746" x="4326" y="-702" settings="{z:2}" assetPackage="fa"/>
      <obj type="GraphicObj" assetClass="fa_gr_plate_9x5_09" id="749" x="4326" y="-642" settings="{z:2}" assetPackage="fa"/>
      <obj type="GraphicObj" assetClass="fa_gr_plate_9x5_09" id="750" x="4434" y="-642" settings="{z:2}" assetPackage="fa"/>
      <obj type="GraphicObj" assetClass="fa_gr_plate_9x5_09" id="752" x="4650" y="-642" settings="{z:2}" assetPackage="fa"/>
      <obj type="GraphicObj" assetClass="fa_gr_plate_9x5_09" id="753" x="4758" y="-642" settings="{z:2}" assetPackage="fa"/>
      <obj type="BasicPhysicsObj" assetClass="fa_gr_plate_9x5_01" id="755" x="4650" y="-882" settings="{z:2}" assetPackage="fa"/>
      <obj type="BasicPhysicsObj" assetClass="fa_gr_plate_9x5_01" id="756" x="4542" y="-882" settings="{z:2}" assetPackage="fa"/>
      <obj type="BasicPhysicsObj" assetClass="fa_gr_plate_9x5_01" id="757" x="4758" y="-882" settings="{z:2}" assetPackage="fa"/>
      <obj type="GraphicObj" assetClass="fa_gr_plate_9x5_09" id="759" x="4218" y="-522" settings="{z:2}" assetPackage="fa"/>
      <obj type="GraphicObj" assetClass="fa_gr_plate_9x5_09" id="760" x="4218" y="-462" settings="{z:2}" assetPackage="fa"/>
      <obj type="GraphicObj" assetClass="fa_gr_plate_9x5_09" id="761" x="4218" y="-402" settings="{z:2}" assetPackage="fa"/>
      <obj type="GraphicObj" assetClass="fa_gr_plate_9x5_09" id="762" x="4218" y="-342" settings="{z:2}" assetPackage="fa"/>
      <obj type="GraphicObj" assetClass="fa_gr_plate_9x5_09" id="763" x="4218" y="-282" settings="{z:2}" assetPackage="fa"/>
      <obj type="GraphicObj" assetClass="fa_gr_plate_9x5_09" id="768" x="4326" y="-582" settings="{z:2}" assetPackage="fa"/>
      <obj type="GraphicObj" assetClass="fa_gr_plate_9x5_09" id="769" x="4326" y="-522" settings="{z:2}" assetPackage="fa"/>
      <obj type="GraphicObj" assetClass="fa_gr_plate_9x5_09" id="770" x="4326" y="-462" settings="{z:2}" assetPackage="fa"/>
      <obj type="GraphicObj" assetClass="fa_gr_plate_9x5_09" id="771" x="4326" y="-402" settings="{z:2}" assetPackage="fa"/>
      <obj type="GraphicObj" assetClass="fa_gr_plate_9x5_09" id="772" x="4326" y="-342" settings="{z:2}" assetPackage="fa"/>
      <obj type="GraphicObj" assetClass="fa_gr_plate_9x5_09" id="773" x="4326" y="-282" settings="{z:2}" assetPackage="fa"/>
      <obj type="GraphicObj" assetClass="fa_gr_plate_9x5_09" id="774" x="4434" y="-582" settings="{z:2}" assetPackage="fa"/>
      <obj type="GraphicObj" assetClass="fa_gr_plate_9x5_09" id="775" x="4434" y="-522" settings="{z:2}" assetPackage="fa"/>
      <obj type="GraphicObj" assetClass="fa_gr_plate_9x5_09" id="776" x="4434" y="-462" settings="{z:2}" assetPackage="fa"/>
      <obj type="GraphicObj" assetClass="fa_gr_plate_9x5_09" id="777" x="4434" y="-402" settings="{z:2}" assetPackage="fa"/>
      <obj type="GraphicObj" assetClass="fa_gr_plate_9x5_09" id="778" x="4434" y="-342" settings="{z:2}" assetPackage="fa"/>
      <obj type="GraphicObj" assetClass="fa_gr_plate_9x5_09" id="779" x="4434" y="-282" settings="{z:2}" assetPackage="fa"/>
      <obj type="BasicPhysicsObj" assetClass="fa_gr_plate_9x5_01" id="780" x="3786" y="-522" settings="{z:2}" assetPackage="fa"/>
      <obj type="BasicPhysicsObj" assetClass="fa_gr_plate_9x5_01" id="781" x="3894" y="-522" settings="{z:2}" assetPackage="fa"/>
      <obj type="BasicPhysicsObj" assetClass="fa_gr_plate_9x5_01" id="782" x="4002" y="-522" settings="{z:2}" assetPackage="fa"/>
      <obj type="BasicPhysicsObj" assetClass="fa_gr_plate_9x5_01" id="783" x="4110" y="-522" settings="{z:2}" assetPackage="fa"/>
      <obj type="Portal" assetClass="un_ob_portalIn" id="785" x="3950.5" y="-657.5" settings="{z:2,pairedPortalLoc:{y:-954.5,x:4655.5}}" assetPackage="un"/>
      <obj type="PickupObj" assetClass="un_ob_win_04_big" id="790" x="4091.5" y="-608.5" settings="{z:6}" assetPackage="un"/>
      <obj type="PickupObj" assetClass="un_ob_win_04_big" id="791" x="4088.5" y="-671.5" settings="{z:6}" assetPackage="un"/>
      <obj type="GraphicObj" assetClass="fa_gr_plate_9x5_09" id="794" x="4650" y="-582" settings="{z:2}" assetPackage="fa"/>
      <obj type="GraphicObj" assetClass="fa_gr_plate_9x5_09" id="795" x="4650" y="-522" settings="{z:2}" assetPackage="fa"/>
      <obj type="GraphicObj" assetClass="fa_gr_plate_9x5_09" id="796" x="4650" y="-462" settings="{z:2}" assetPackage="fa"/>
      <obj type="GraphicObj" assetClass="fa_gr_plate_9x5_09" id="797" x="4650" y="-402" settings="{z:2}" assetPackage="fa"/>
      <obj type="GraphicObj" assetClass="fa_gr_plate_9x5_09" id="798" x="4758" y="-582" settings="{z:2}" assetPackage="fa"/>
      <obj type="GraphicObj" assetClass="fa_gr_plate_9x5_09" id="799" x="4758" y="-522" settings="{z:2}" assetPackage="fa"/>
      <obj type="GraphicObj" assetClass="fa_gr_plate_9x5_09" id="800" x="4758" y="-462" settings="{z:2}" assetPackage="fa"/>
      <obj type="GraphicObj" assetClass="fa_gr_plate_9x5_09" id="801" x="4758" y="-402" settings="{z:2}" assetPackage="fa"/>
      <obj type="BasicPhysicsObj" assetClass="fa_gr_plate_9x5_01" id="802" x="4758" y="-942" settings="{z:2}" assetPackage="fa"/>
      <obj type="BasicPhysicsObj" assetClass="fa_gr_plate_9x5_01" id="803" x="4758" y="-1002" settings="{z:2}" assetPackage="fa"/>
      <obj type="BasicPhysicsObj" assetClass="fa_gr_plate_9x5_01" id="804" x="4758" y="-1062" settings="{z:2}" assetPackage="fa"/>
      <obj type="BasicPhysicsObj" assetClass="fa_gr_plate_9x5_01" id="805" x="4758" y="-1182" settings="{z:2}" assetPackage="fa"/>
      <obj type="BasicPhysicsObj" assetClass="fa_gr_plate_9x5_01" id="812" x="4758" y="-1122" settings="{z:2}" assetPackage="fa"/>
      <obj type="BasicPhysicsObj" assetClass="fa_gr_plate_9x5_01" id="817" x="3678" y="-762" settings="{z:2}" assetPackage="fa"/>
      <obj type="BasicPhysicsObj" assetClass="fa_gr_plate_9x5_01" id="818" x="3678" y="-702" settings="{z:2}" assetPackage="fa"/>
      <obj type="BasicPhysicsObj" assetClass="fa_gr_plate_9x5_01" id="819" x="3678" y="-642" settings="{z:2}" assetPackage="fa"/>
      <obj type="BasicPhysicsObj" assetClass="fa_gr_plate_9x5_01" id="820" x="3678" y="-582" settings="{z:2}" assetPackage="fa"/>
      <obj type="BasicPhysicsObj" assetClass="fa_gr_plate_9x5_01" id="821" x="4218" y="-582" settings="{z:2}" assetPackage="fa"/>
      <obj type="BasicPhysicsObj" assetClass="fa_gr_plate_9x5_01" id="822" x="4218" y="-642" settings="{z:2}" assetPackage="fa"/>
      <obj type="BasicPhysicsObj" assetClass="fa_gr_plate_9x5_01" id="823" x="4218" y="-702" settings="{z:2}" assetPackage="fa"/>
      <obj type="BasicPhysicsObj" assetClass="fa_gr_plate_9x5_01" id="824" x="4218" y="-762" settings="{z:2}" assetPackage="fa"/>
      <obj type="GraphicObj" assetClass="fa_gr_plate_9x5_09" id="825" x="4542" y="-582" settings="{z:2}" assetPackage="fa"/>
      <obj type="GraphicObj" assetClass="fa_gr_plate_9x5_09" id="826" x="4542" y="-522" settings="{z:2}" assetPackage="fa"/>
      <obj type="GraphicObj" assetClass="fa_gr_plate_9x5_09" id="827" x="4542" y="-462" settings="{z:2}" assetPackage="fa"/>
      <obj type="GraphicObj" assetClass="fa_gr_plate_9x5_09" id="828" x="4542" y="-402" settings="{z:2}" assetPackage="fa"/>
      <obj type="BasicPhysicsObj" assetClass="fa_gr_plate_9x5_02" id="829" x="3786" y="-462" settings="{z:2}" assetPackage="fa"/>
      <obj type="BasicPhysicsObj" assetClass="fa_gr_plate_9x5_02" id="830" x="3894" y="-462" settings="{z:2}" assetPackage="fa"/>
      <obj type="BasicPhysicsObj" assetClass="fa_gr_plate_9x5_02" id="831" x="4002" y="-462" settings="{z:2}" assetPackage="fa"/>
      <obj type="BasicPhysicsObj" assetClass="fa_gr_plate_9x5_02" id="832" x="4110" y="-462" settings="{z:2}" assetPackage="fa"/>
      <obj type="GraphicObj" assetClass="fa_gr_plate_9x5_09" id="833" x="3678" y="-402" settings="{z:2}" assetPackage="fa"/>
      <obj type="BasicPhysicsObj" assetClass="fa_gr_pipe_2x12_v" id="835" x="4141" y="-699" settings="{z:3}" assetPackage="fa"/>
      <obj type="BasicPhysicsObj" assetClass="fa_gr_pipe_valveEnd" id="836" x="4141" y="-774" settings="{z:3}" assetPackage="fa"/>
      <obj type="BasicPhysicsObj" assetClass="fa_gr_pipe_2x12_v" id="837" x="4141" y="-561" settings="{z:1}" assetPackage="fa"/>
      <obj type="BasicPhysicsObj" assetClass="fa_gr_pipe_2x12_v" id="839" x="4294" y="-1016" settings="{z:1}" assetPackage="fa"/>
      <obj type="BasicPhysicsObj" assetClass="fa_gr_pipe_bend_3" id="840" x="4140.95" y="-1066.55" settings="{z:2}" assetPackage="fa"/>
      <obj type="BasicPhysicsObj" assetClass="fa_gr_pipe_2x12_v" id="842" x="4153" y="-975" settings="{z:1}" assetPackage="fa"/>
      <obj type="BasicPhysicsObj" assetClass="fa_gr_pipe_conn1" id="844" x="4294" y="-1120.95" settings="{z:2}" assetPackage="fa"/>
      <obj type="BasicPhysicsObj" assetClass="fa_gr_pipe_bend_4" id="845" x="4306" y="-1217" settings="{z:2}" assetPackage="fa"/>
      <obj type="BasicPhysicsObj" assetClass="fa_gr_pipe_2x6_h" id="846" x="4354" y="-1121" settings="{z:1}" assetPackage="fa"/>
      <obj type="BasicPhysicsObj" assetClass="fa_gr_pipe_2x3_v" id="847" x="4294" y="-1175" settings="{z:2}" assetPackage="fa"/>
      <obj type="PickupObj" assetClass="un_ob_win_01_small" id="848" x="4355.5" y="-1176.5" settings="{z:6}" assetPackage="un"/>
      <obj type="BasicPhysicsObj" assetClass="fa_gr_pipe_2x6_h" id="849" x="4425" y="-1122" settings="{z:1}" assetPackage="fa"/>
      <obj type="BasicPhysicsObj" assetClass="fa_gr_pipe_bend_3" id="850" x="4483.9" y="-1110.55" settings="{z:2}" assetPackage="fa"/>
      <obj type="BasicPhysicsObj" assetClass="fa_gr_pipe_bend_4" id="853" x="4604" y="-1009.95" settings="{z:2}" assetPackage="fa"/>
      <obj type="BasicPhysicsObj" assetClass="fa_gr_plate_9x5_01" id="854" x="4758" y="-1242" settings="{z:2}" assetPackage="fa"/>
      <obj type="BasicPhysicsObj" assetClass="fa_gr_plate_9x5_01" id="855" x="4758" y="-1302" settings="{z:2}" assetPackage="fa"/>
      <obj type="BasicPhysicsObj" assetClass="fa_gr_plate_9x5_01" id="856" x="4758" y="-1362" settings="{z:2}" assetPackage="fa"/>
      <obj type="BasicPhysicsObj" assetClass="fa_gr_plate_9x5_01" id="857" x="4758" y="-1422" settings="{z:2}" assetPackage="fa"/>
      <obj type="BasicPhysicsObj" assetClass="fa_gr_pipe_2x12_h" id="858" x="4696" y="-1022" settings="{z:1}" assetPackage="fa"/>
      <obj type="PickupObj" assetClass="un_ob_win_01_small" id="859" x="4403.5" y="-1176.5" settings="{z:6}" assetPackage="un"/>
      <obj type="PickupObj" assetClass="un_ob_win_01_small" id="860" x="4451.5" y="-1176.5" settings="{z:6}" assetPackage="un"/>
      <obj type="PickupObj" assetClass="un_ob_win_micro" id="861" x="4193.5" y="-990.5" settings="{z:6}" assetPackage="un"/>
      <obj type="PickupObj" assetClass="un_ob_win_micro" id="862" x="4217.5" y="-990.5" settings="{z:6}" assetPackage="un"/>
      <obj type="PickupObj" assetClass="un_ob_win_micro" id="863" x="4241.5" y="-990.5" settings="{z:6}" assetPackage="un"/>
      <obj type="PickupObj" assetClass="un_ob_win_micro" id="864" x="4241.5" y="-1014.5" settings="{z:6}" assetPackage="un"/>
      <obj type="PickupObj" assetClass="un_ob_win_micro" id="865" x="4217.5" y="-1014.5" settings="{z:6}" assetPackage="un"/>
      <obj type="PickupObj" assetClass="un_ob_win_micro" id="866" x="4193.5" y="-1014.5" settings="{z:6}" assetPackage="un"/>
      <obj type="PickupObj" assetClass="un_ob_win_micro" id="867" x="4193.5" y="-1038.5" settings="{z:6}" assetPackage="un"/>
      <obj type="PickupObj" assetClass="un_ob_win_micro" id="868" x="4217.5" y="-1038.5" settings="{z:6}" assetPackage="un"/>
      <obj type="PickupObj" assetClass="un_ob_win_micro" id="869" x="4241.5" y="-1038.5" settings="{z:6}" assetPackage="un"/>
    </plane>
  </planes>
</level>